bervr_messenger_server-2.1.8.data/scripts/server_run.py
server/__init__.py
server/server.py
server/server_run.py
server/common/__init__.py
server/common/decor.py
server/common/descriptors.py
server/common/errors.py
server/common/metaclasses.py
server/common/utils.py
server/common/variables.py
server/logs/__init__.py
server/logs/conf/__init__.py
server/logs/conf/server_log_config.py
server/server/__init__.py
server/server/add_user.py
server/server/database.py
server/server/remove_user.py
server/server/server.ini
server/server/server.py
server/server/server_gui.py
server/server/stat_window.py
bervr_messenger_server-2.1.8.dist-info/METADATA
bervr_messenger_server-2.1.8.dist-info/WHEEL
bervr_messenger_server-2.1.8.dist-info/top_level.txt
bervr_messenger_server-2.1.8.dist-info/RECORD
