Metadata-Version: 2.1
Name: bervr-messenger-server
Version: 2.1.8
Summary: A server part for messenger
Author: Aleksandr Filippov
Author-email: bervrr@gmail.com
Requires-Dist: PyQt5
Requires-Dist: SQLAlchemy
Requires-Dist: pycryptodome
Requires-Dist: pycryptodomex
Requires-Dist: chardet
